wakeonlan/__init__.py
wakeonlan/__main__.py
wakeonlan/autocomplete.ps1
wakeonlan/autocomplete.sh
wakeonlan/py.typed
wakeonlan/wakeonlan.py
eg.wakeonlan-1.3.dist-info/LICENSE.txt
eg.wakeonlan-1.3.dist-info/METADATA
eg.wakeonlan-1.3.dist-info/WHEEL
eg.wakeonlan-1.3.dist-info/entry_points.txt
eg.wakeonlan-1.3.dist-info/top_level.txt
eg.wakeonlan-1.3.dist-info/RECORD
